yoctolib/__init__.py
yoctolib/yocto_accelerometer.py
yoctolib/yocto_accelerometer_aio.py
yoctolib/yocto_altitude.py
yoctolib/yocto_altitude_aio.py
yoctolib/yocto_anbutton.py
yoctolib/yocto_anbutton_aio.py
yoctolib/yocto_angularspeed.py
yoctolib/yocto_angularspeed_aio.py
yoctolib/yocto_api.py
yoctolib/yocto_api_aio.py
yoctolib/yocto_arithmeticsensor.py
yoctolib/yocto_arithmeticsensor_aio.py
yoctolib/yocto_audioin.py
yoctolib/yocto_audioin_aio.py
yoctolib/yocto_audioout.py
yoctolib/yocto_audioout_aio.py
yoctolib/yocto_bluetoothlink.py
yoctolib/yocto_bluetoothlink_aio.py
yoctolib/yocto_buzzer.py
yoctolib/yocto_buzzer_aio.py
yoctolib/yocto_carbondioxide.py
yoctolib/yocto_carbondioxide_aio.py
yoctolib/yocto_cellular.py
yoctolib/yocto_cellular_aio.py
yoctolib/yocto_colorled.py
yoctolib/yocto_colorled_aio.py
yoctolib/yocto_colorledcluster.py
yoctolib/yocto_colorledcluster_aio.py
yoctolib/yocto_colorsensor.py
yoctolib/yocto_colorsensor_aio.py
yoctolib/yocto_compass.py
yoctolib/yocto_compass_aio.py
yoctolib/yocto_counter.py
yoctolib/yocto_counter_aio.py
yoctolib/yocto_current.py
yoctolib/yocto_current_aio.py
yoctolib/yocto_currentloopoutput.py
yoctolib/yocto_currentloopoutput_aio.py
yoctolib/yocto_daisychain.py
yoctolib/yocto_daisychain_aio.py
yoctolib/yocto_digitalio.py
yoctolib/yocto_digitalio_aio.py
yoctolib/yocto_display.py
yoctolib/yocto_display_aio.py
yoctolib/yocto_dualpower.py
yoctolib/yocto_dualpower_aio.py
yoctolib/yocto_files.py
yoctolib/yocto_files_aio.py
yoctolib/yocto_genericsensor.py
yoctolib/yocto_genericsensor_aio.py
yoctolib/yocto_gps.py
yoctolib/yocto_gps_aio.py
yoctolib/yocto_groundspeed.py
yoctolib/yocto_groundspeed_aio.py
yoctolib/yocto_gyro.py
yoctolib/yocto_gyro_aio.py
yoctolib/yocto_hubport.py
yoctolib/yocto_hubport_aio.py
yoctolib/yocto_humidity.py
yoctolib/yocto_humidity_aio.py
yoctolib/yocto_i2cport.py
yoctolib/yocto_i2cport_aio.py
yoctolib/yocto_inputcapture.py
yoctolib/yocto_inputcapture_aio.py
yoctolib/yocto_inputchain.py
yoctolib-2.1.11632.dist-info/METADATA
yoctolib-2.1.11632.dist-info/WHEEL
yoctolib-2.1.11632.dist-info/licenses/LICENSE.txt
yoctolib-2.1.11632.dist-info/RECORD
