Metadata-Version: 2.4
Name: yoctolib
Version: 2.1.11632
Summary: Yoctopuce PurePython API v2.0
Project-URL: Homepage, https://www.yoctopuce.com/EN/libraries.php
Project-URL: Documentation, https://www.yoctopuce.com/EN/doc/reference/yoctolib-typedpython-EN.html
Project-URL: Repository, https://github.com/yoctopuce/yoctolib_typedpython
Project-URL: Issues, https://github.com/yoctopuce/yoctolib_typedpython/issues
Project-URL: Changelog, https://www.yoctopuce.com/EN/release_notes.php?sessionid=-1&file=YoctoLib.typedpython.57762.zip
Author-email: Yoctopuce <dev@yoctopuce.com>
License: License information
License-File: LICENSE.txt
Classifier: Development Status :: 4 - Beta
Classifier: Intended Audience :: Customer Service
Classifier: Intended Audience :: Developers
Classifier: Intended Audience :: Science/Research
Classifier: Natural Language :: English
Classifier: Operating System :: MacOS :: MacOS X
Classifier: Operating System :: Microsoft :: Windows :: Windows 7
Classifier: Operating System :: Microsoft :: Windows :: Windows 8
Classifier: Operating System :: Microsoft :: Windows :: Windows 8.1
Classifier: Operating System :: Microsoft :: Windows :: Windows 10
Classifier: Operating System :: Microsoft :: Windows :: Windows 11
Classifier: Operating System :: Unix
Classifier: Programming Language :: Python :: 3.8
Classifier: Programming Language :: Python :: 3.9
Classifier: Programming Language :: Python :: 3.10
Classifier: Programming Language :: Python :: 3.11
Classifier: Programming Language :: Python :: 3.12
Classifier: Programming Language :: Python :: 3.13
Requires-Python: >=3.8
